{
  "ID": "157882",
  "NameSubtext_lang": "",
  "Description_lang": "Inflicts $s1 Physical damage to all enemies on impact, and an additional $s2 Physical damage every $t2 sec for $d. If interrupted, increases cast speed by $186919s1%.",
  "AuraDescription_lang": "Inflicting $s2 Physical damage every $t2 sec.",
  "Attributes_0": "0",
  "Attributes_1": "1160",
  "Attributes_2": "4194308",
  "Attributes_3": "256",
  "Attributes_4": "0",
  "Attributes_5": "0",
  "Attributes_6": "0",
  "Attributes_7": "64",
  "Attributes_8": "0",
  "Attributes_9": "0",
  "Attributes_10": "0",
  "Attributes_11": "0",
  "Attributes_12": "0",
  "Attributes_13": "0",
  "Attributes_14": "0",
  "Attributes_15": "0",
  "DifficultyID": "0",
  "CastingTimeIndex": "19",
  "DurationIndex": "1",
  "PvPDurationIndex": "0",
  "RangeIndex": "187",
  "SchoolMask": "1",
  "Speed": "0",
  "LaunchDelay": "0",
  "MinDuration": "0",
  "SpellIconFileDataID": "132352",
  "ActiveIconFileDataID": "0",
  "ContentTuningID": "0",
  "ShowFutureSpellPlayerConditionID": "0",
  "SpellVisualScript": "0",
  "ActiveSpellVisualScript": "0",
  "SpellID": "183917"
}