{
  "ID": "17609",
  "NameSubtext_lang": "",
  "Description_lang": "Places a ward on an ally that heals them for $33110s1 the next time they take damage, and then jumps to another ally within $155793a1 yds. Jumps up to $s1 times and lasts $41635d after each jump.",
  "AuraDescription_lang": "",
  "Attributes_0": "65536",
  "Attributes_1": "0",
  "Attributes_2": "524288",
  "Attributes_3": "67108864",
  "Attributes_4": "1048576",
  "Attributes_5": "0",
  "Attributes_6": "0",
  "Attributes_7": "1073741824",
  "Attributes_8": "4096",
  "Attributes_9": "0",
  "Attributes_10": "0",
  "Attributes_11": "0",
  "Attributes_12": "0",
  "Attributes_13": "1",
  "Attributes_14": "0",
  "Attributes_15": "0",
  "DifficultyID": "0",
  "CastingTimeIndex": "1",
  "DurationIndex": "0",
  "PvPDurationIndex": "0",
  "RangeIndex": "5",
  "SchoolMask": "2",
  "Speed": "0",
  "LaunchDelay": "0",
  "MinDuration": "0",
  "SpellIconFileDataID": "135944",
  "ActiveIconFileDataID": "0",
  "ContentTuningID": "0",
  "ShowFutureSpellPlayerConditionID": "0",
  "SpellVisualScript": "0",
  "ActiveSpellVisualScript": "0",
  "SpellID": "33076",
  "name_blz": {
    "en_US": "Prayer of Mending",
    "es_MX": "Rezo de alivio",
    "pt_BR": "Prece da Recomposi\u00e7\u00e3o",
    "de_DE": "Gebet der Besserung",
    "en_GB": "Prayer of Mending",
    "es_ES": "Rezo de alivio",
    "fr_FR": "Pri\u00e8re de gu\u00e9rison",
    "it_IT": "Preghiera di Guarigione",
    "ru_RU": "\u041c\u043e\u043b\u0438\u0442\u0432\u0430 \u0432\u043e\u0441\u0441\u0442\u0430\u043d\u043e\u0432\u043b\u0435\u043d\u0438\u044f",
    "ko_KR": "\ud68c\ubcf5\uc758 \uae30\uc6d0",
    "zh_TW": "\u7652\u5408\u79b1\u8a00",
    "zh_CN": "\u6108\u5408\u7977\u8a00"
  },
  "description_blz": {
    "en_US": "Places a ward on an ally that heals them for 3,391 the next time they take damage, and then jumps to another ally within 30 yds. Jumps up to 4 times and lasts 30 sec after each jump.",
    "es_MX": "Coloca un resguardo sobre un aliado que lo sanar\u00e1 por 3,383 p. la pr\u00f3xima vez que reciba da\u00f1o y luego salta a otro aliado en un radio de 30 m. Salta hasta 4 veces y dura 30 s despu\u00e9s de cada salto.",
    "pt_BR": "Lan\u00e7a uma prote\u00e7\u00e3o sobre um aliado, restaurando 3.372 pontos de vida da pr\u00f3xima vez que ele receber dano. Em seguida, propaga-se para outro aliado em um raio de 30 m. Propaga-se at\u00e9 4 vezes e dura 30 s ap\u00f3s cada propaga\u00e7\u00e3o.",
    "de_DE": "Belegt einen Verb\u00fcndeten mit einem Zauberschutz, der ihn um 3.307 Gesundheit heilt, wenn er das n\u00e4chste Mal Schaden erleidet. Anschlie\u00dfend springt der Schutz auf einen anderen Verb\u00fcndeten innerhalb von 30 Metern \u00fcber. Springt bis zu 4-mal und h\u00e4lt nach jedem Sprung 30 Sek. lang an.",
    "en_GB": "Places a ward on an ally that heals them for 3,358 the next time they take damage, and then jumps to another ally within 30 yds. Jumps up to 4 times and lasts 30 sec after each jump.",
    "es_ES": "Coloca un resguardo sobre un aliado que lo sanar\u00e1 3450 p. la pr\u00f3xima vez que reciba da\u00f1o y luego salta a otro aliado en un radio de 30 m. Salta hasta 4 veces y dura 30 s tras cada salto.",
    "fr_FR": "Place sur un alli\u00e9 une protection qui lui rend 3415\u00a0points de vie la prochaine fois qu\u2019il subit des d\u00e9g\u00e2ts, puis se propage \u00e0 un autre alli\u00e9 se trouvant \u00e0 moins de 30\u00a0m\u00e8tres. Change de cible un maximum de 4\u00a0fois et dure 30 s apr\u00e8s chaque changement.",
    "it_IT": "Lancia una preghiera su un alleato, curandolo di 3.374 la successiva volta che subisce danni e passando poi su un altro alleato entro 30 m, per un massimo di 4 volte. Dura fino a un massimo di 30 s dopo ogni passaggio.",
    "ru_RU": "\u041f\u0440\u0438\u043c\u0435\u043d\u044f\u0435\u0442 \u043a \u0441\u043e\u044e\u0437\u043d\u0438\u043a\u0443 \u0437\u0430\u043a\u043b\u0438\u043d\u0430\u043d\u0438\u0435, \u043a\u043e\u0442\u043e\u0440\u043e\u0435 \u0432\u043e\u0441\u043f\u043e\u043b\u043d\u044f\u0435\u0442 3459 \u0435\u0434. \u0437\u0434\u043e\u0440\u043e\u0432\u044c\u044f \u043f\u0440\u0438 \u0441\u043b\u0435\u0434\u0443\u044e\u0449\u0435\u043c \u043f\u043e\u043b\u0443\u0447\u0435\u043d\u0438\u0438 \u0443\u0440\u043e\u043d\u0430, \u043f\u043e\u0441\u043b\u0435 \u0447\u0435\u0433\u043e \u043f\u0435\u0440\u0435\u0445\u043e\u0434\u0438\u0442 \u043a \u0434\u0440\u0443\u0433\u043e\u043c\u0443 \u0441\u043e\u044e\u0437\u043d\u0438\u043a\u0443 \u0432 \u043f\u0440\u0435\u0434\u0435\u043b\u0430\u0445 30 \u043c. \u041c\u0430\u043a\u0441\u0438\u043c\u0443\u043c \u043f\u0435\u0440\u0435\u0445\u043e\u0434\u043e\u0432 \u2013 4; \u0434\u0435\u0439\u0441\u0442\u0432\u0443\u0435\u0442 30 \u0441\u0435\u043a. \u043f\u043e\u0441\u043b\u0435 \u043a\u0430\u0436\u0434\u043e\u0433\u043e \u043f\u0435\u0440\u0435\u0445\u043e\u0434\u0430.",
    "ko_KR": "\uc544\uad70\uc5d0\uac8c \uc218\ud638\ubb3c\uc744 \ubd80\ucc29\ud558\uc5ec, \ub2e4\uc74c \ud53c\ud574\ub97c \uc785\uc744 \ub54c 3,302\uc758 \uc0dd\uba85\ub825\uc744 \ud68c\ubcf5\uc2dc\ud0b5\ub2c8\ub2e4. \uc774\ud6c4 \ud68c\ubcf5\uc758 \uae30\uc6d0\uc740 30\ubbf8\ud130 \ubc18\uacbd \ub0b4\uc758 \uc544\uad70\uc5d0\uac8c \uc804\ub2ec\ub429\ub2c8\ub2e4. \ucd5c\ub300 4\ubc88\uae4c\uc9c0 \uc804\ub2ec\ub418\uba70, \ub9e4 \uc804\ub2ec \uc2dc 30\ucd08 \ub3d9\uc548 \uc9c0\uc18d\ub429\ub2c8\ub2e4.",
    "zh_TW": "\u5728\u4e00\u540d\u76df\u53cb\u8eab\u4e0a\u65bd\u653e\u4e00\u9053\u7d50\u754c\uff0c\u5728\u5176\u4e0b\u6b21\u53d7\u5230\u50b7\u5bb3\u6642\uff0c\u70ba\u5176\u6cbb\u76423,421\u9ede\u751f\u547d\u529b\uff0c\u4e26\u8df3\u81f330\u78bc\u5167\u7684\u53e6\u4e00\u540d\u76df\u53cb\u8eab\u4e0a\u3002\u6700\u591a\u8df3\u8e8d4\u6b21\uff0c\u4e26\u4e14\u6bcf\u6b21\u8df3\u8e8d\u5f8c\u53ef\u6301\u7e8c30\u79d2\u3002",
    "zh_CN": "\u4e3a\u4e00\u540d\u76df\u53cb\u65bd\u52a0\u7ed3\u754c\uff0c\u4f7f\u5176\u5728\u4e0b\u4e00\u6b21\u53d7\u5230\u4f24\u5bb3\u65f6\u6062\u590d3,330\u70b9\u751f\u547d\u503c\uff0c\u89e6\u53d1\u4e4b\u540e\u4f1a\u8df3\u8f6c\u523030\u7801\u8303\u56f4\u5185\u7684\u53e6\u4e00\u540d\u76df\u53cb\u8eab\u4e0a\u3002\u6700\u591a\u53ef\u8f6c\u79fb4\u6b21\uff0c\u6bcf\u6b21\u8f6c\u79fb\u540e\u5728\u76ee\u6807\u8eab\u4e0a\u6301\u7eed30\u79d2\u3002"
  }
}