{
  "ID": "634600",
  "NameSubtext_lang": "",
  "Description_lang": "The Broodkeeper's diligent care links her life essence to the unhatched eggs, preventing all damage below $375809s2% remaining health. This effect stacks for each intact egg in the room.Additionally, this aura increases the damage done of nearby allies by $396177s1%, decreases damage taken by $396177s2%, and heals $396177s3% of their total health every second for $396177D. This effect stacks.",
  "AuraDescription_lang": "Prevents all damage below $375809s2% remaining health.Empowers nearby allies increasing damage done, decreasing damage taken, and healing every second.",
  "Attributes_0": "0",
  "Attributes_1": "0",
  "Attributes_2": "0",
  "Attributes_3": "0",
  "Attributes_4": "1",
  "Attributes_5": "512",
  "Attributes_6": "0",
  "Attributes_7": "0",
  "Attributes_8": "0",
  "Attributes_9": "0",
  "Attributes_10": "0",
  "Attributes_11": "0",
  "Attributes_12": "0",
  "Attributes_13": "0",
  "Attributes_14": "0",
  "Attributes_15": "0",
  "DifficultyID": "0",
  "CastingTimeIndex": "1",
  "DurationIndex": "21",
  "PvPDurationIndex": "0",
  "RangeIndex": "1",
  "SchoolMask": "64",
  "Speed": "0",
  "LaunchDelay": "0",
  "MinDuration": "0",
  "SpellIconFileDataID": "4509429",
  "ActiveIconFileDataID": "0",
  "ContentTuningID": "0",
  "ShowFutureSpellPlayerConditionID": "0",
  "SpellVisualScript": "0",
  "ActiveSpellVisualScript": "0",
  "SpellID": "375809"
}