{
  "ID": "636244",
  "NameSubtext_lang": "",
  "Description_lang": "Stomp the ground, commanding flames to radiate outward from your position, dealing $394393s1 Fire damage split between all enemies struck and granting you a $394393s2 shield for $382058d. After a delay, the flames return, dealing the same damage and refreshing the shield.Damage and absorption are increased for each enemy struck, up to $s3 enemies.",
  "AuraDescription_lang": "",
  "Attributes_0": "0",
  "Attributes_1": "268435456",
  "Attributes_2": "0",
  "Attributes_3": "0",
  "Attributes_4": "0",
  "Attributes_5": "0",
  "Attributes_6": "1024",
  "Attributes_7": "0",
  "Attributes_8": "4096",
  "Attributes_9": "0",
  "Attributes_10": "8192",
  "Attributes_11": "4",
  "Attributes_12": "0",
  "Attributes_13": "0",
  "Attributes_14": "0",
  "Attributes_15": "0",
  "DifficultyID": "0",
  "CastingTimeIndex": "1",
  "DurationIndex": "551",
  "PvPDurationIndex": "0",
  "RangeIndex": "1",
  "SchoolMask": "4",
  "Speed": "0",
  "LaunchDelay": "0",
  "MinDuration": "0",
  "SpellIconFileDataID": "1387353",
  "ActiveIconFileDataID": "0",
  "ContentTuningID": "0",
  "ShowFutureSpellPlayerConditionID": "0",
  "SpellVisualScript": "0",
  "ActiveSpellVisualScript": "0",
  "SpellID": "377449"
}