{
  "ID": "721630",
  "NameSubtext_lang": "",
  "Description_lang": "Become trapped under a pile of rubble.",
  "AuraDescription_lang": "Trapped under a pile of rubble from the crash of Dalaran.",
  "Attributes_0": "605356032",
  "Attributes_1": "2048",
  "Attributes_2": "0",
  "Attributes_3": "805306368",
  "Attributes_4": "8192",
  "Attributes_5": "536870912",
  "Attributes_6": "135168",
  "Attributes_7": "0",
  "Attributes_8": "0",
  "Attributes_9": "0",
  "Attributes_10": "0",
  "Attributes_11": "0",
  "Attributes_12": "0",
  "Attributes_13": "0",
  "Attributes_14": "0",
  "Attributes_15": "0",
  "DifficultyID": "0",
  "CastingTimeIndex": "1",
  "DurationIndex": "5",
  "PvPDurationIndex": "0",
  "RangeIndex": "135",
  "SchoolMask": "1",
  "Speed": "0",
  "LaunchDelay": "0",
  "MinDuration": "0",
  "SpellIconFileDataID": "132846",
  "ActiveIconFileDataID": "0",
  "ContentTuningID": "0",
  "ShowFutureSpellPlayerConditionID": "0",
  "SpellVisualScript": "0",
  "ActiveSpellVisualScript": "0",
  "SpellID": "429498"
}