{
  "ID": "39782",
  "NameSubtext_lang": "",
  "Description_lang": "Infused with the spirit of Midsummer.",
  "AuraDescription_lang": "Infused with the spirit of Midsummer.",
  "Attributes_0": "64",
  "Attributes_1": "0",
  "Attributes_2": "0",
  "Attributes_3": "0",
  "Attributes_4": "0",
  "Attributes_5": "0",
  "Attributes_6": "0",
  "Attributes_7": "0",
  "Attributes_8": "0",
  "Attributes_9": "0",
  "Attributes_10": "0",
  "Attributes_11": "0",
  "Attributes_12": "0",
  "Attributes_13": "0",
  "Attributes_14": "0",
  "Attributes_15": "0",
  "DifficultyID": "0",
  "CastingTimeIndex": "1",
  "DurationIndex": "0",
  "PvPDurationIndex": "0",
  "RangeIndex": "1",
  "SchoolMask": "1",
  "Speed": "0",
  "LaunchDelay": "0",
  "MinDuration": "0",
  "SpellIconFileDataID": "135819",
  "ActiveIconFileDataID": "0",
  "ContentTuningID": "0",
  "ShowFutureSpellPlayerConditionID": "0",
  "SpellVisualScript": "0",
  "ActiveSpellVisualScript": "0",
  "SpellID": "58933",
  "name_blz": {
    "en_US": "Has Full Midsummer Set",
    "es_MX": "Tiene conjunto completo del solsticio de verano",
    "pt_BR": "Tem Todo o Conjunto de Solst\u00edcio",
    "de_DE": "Hat das volle Sonnenwendset",
    "en_GB": "Has Full Midsummer Set",
    "es_ES": "Tiene conjunto completo del solsticio de verano",
    "fr_FR": "A un ensemble du Solstice d'\u00e9t\u00e9 complet",
    "it_IT": "Completo di Mezza Estate",
    "ru_RU": "\u041f\u043e\u043b\u043d\u044b\u0439 \u043a\u043e\u043c\u043f\u043b\u0435\u043a\u0442 \u0421\u043e\u043b\u043d\u0446\u0435\u0432\u043e\u0440\u043e\u0442\u0430",
    "ko_KR": "\ud55c\uc5ec\ub984 \ucd95\uc81c \uc758\uc0c1 \ubaa8\ub450 \uac16\ucd94\uae30",
    "zh_TW": "\u64c1\u6709\u5168\u5957\u4ef2\u590f\u7bc0\u5957\u88dd",
    "zh_CN": "\u5168\u5957\u4ef2\u590f\u5957\u88c5"
  },
  "description_blz": {
    "en_US": "Infused with the spirit of Midsummer.",
    "es_MX": "Imbuido del esp\u00edritu del Solsticio.",
    "pt_BR": "Infuso com o esp\u00edrito do Solst\u00edcio.",
    "de_DE": "Vom Geist des Sonnenwendfests erf\u00fcllt.",
    "en_GB": "Infused with the spirit of Midsummer.",
    "es_ES": "Imbuido del esp\u00edritu del Solsticio.",
    "fr_FR": "Impr\u00e9gn\u00e9 de l'esprit du Solstice.",
    "it_IT": "Infonde in te lo spirito di Mezza Estate.",
    "ru_RU": "\u0414\u0443\u0445 \u043e\u0433\u043d\u0435\u043d\u043d\u043e\u0433\u043e \u0421\u043e\u043b\u043d\u0446\u0435\u0432\u043e\u0440\u043e\u0442\u0430.",
    "ko_KR": "\ud55c\uc5ec\ub984 \ucd95\uc81c\uc758 \uc815\uc2e0\uc73c\ub85c \ucda9\ub9cc\ud569\ub2c8\ub2e4.",
    "zh_TW": "\u5145\u6eff\u4ef2\u590f\u7bc0\u7684\u7cbe\u795e\u3002",
    "zh_CN": "\u4ef2\u590f\u4e4b\u9b42\u7684\u6c14\u606f\u8426\u7ed5\u7740\u4f60\u3002"
  }
}