{
  "ID": "57209",
  "NameSubtext_lang": "",
  "Description_lang": "Krom'gar Sergeant in Overlord Krom'gar's Army.",
  "AuraDescription_lang": "Krom'gar Sergeant in Overlord Krom'gar's Army.",
  "Attributes_0": "-1451229184",
  "Attributes_1": "1056",
  "Attributes_2": "268976133",
  "Attributes_3": "1245184",
  "Attributes_4": "8388736",
  "Attributes_5": "393224",
  "Attributes_6": "12292",
  "Attributes_7": "0",
  "Attributes_8": "0",
  "Attributes_9": "0",
  "Attributes_10": "0",
  "Attributes_11": "0",
  "Attributes_12": "0",
  "Attributes_13": "0",
  "Attributes_14": "0",
  "Attributes_15": "0",
  "DifficultyID": "0",
  "CastingTimeIndex": "1",
  "DurationIndex": "21",
  "PvPDurationIndex": "0",
  "RangeIndex": "1",
  "SchoolMask": "1",
  "Speed": "0",
  "LaunchDelay": "0",
  "MinDuration": "0",
  "SpellIconFileDataID": "236614",
  "ActiveIconFileDataID": "0",
  "ContentTuningID": "0",
  "ShowFutureSpellPlayerConditionID": "0",
  "SpellVisualScript": "0",
  "ActiveSpellVisualScript": "0",
  "SpellID": "78054",
  "name_blz": {
    "en_US": "Krom'gar Sergeant",
    "es_MX": "Sargento Krom'gar",
    "pt_BR": "Sargento de Krom'gar",
    "de_DE": "Unteroffizier von Krom'gar",
    "en_GB": "Krom'gar Sergeant",
    "es_ES": "Sargento Krom'gar",
    "fr_FR": "Sergent de Krom'gar",
    "it_IT": "Sergente Krom'gar",
    "ru_RU": "\u041a\u0440\u043e\u043c'\u0433\u0430\u0440\u0441\u043a\u0438\u0439 \u0441\u0435\u0440\u0436\u0430\u043d\u0442",
    "ko_KR": "\ud06c\ub86c\uac00\ub974 \ud558\uc0ac\uad00",
    "zh_TW": "\u514b\u7f85\u59c6\u52a0\u58eb\u5b98",
    "zh_CN": "\u514b\u7f57\u59c6\u52a0\u4e2d\u58eb"
  },
  "description_blz": {
    "en_US": "Krom'gar Sergeant in Overlord Krom'gar's Army.",
    "es_MX": "Sargento Krom'gar en el ej\u00e9rcito del se\u00f1or supremo Krom'gar.",
    "pt_BR": "Sargento de Krom'gar no ex\u00e9rcito do Lorde Supremo Krom'gar.",
    "de_DE": "Unteroffizier von Krom'gar in der Armee von Oberanf\u00fchrer Krom'gar.",
    "en_GB": "Krom'gar Sergeant in Overlord Krom'gar's Army.",
    "es_ES": "Sargento Krom'gar en el ej\u00e9rcito del se\u00f1or supremo Krom'gar.",
    "fr_FR": "Sergent de Krom'gar dans l'arm\u00e9e du suzerain Krom'gar.",
    "it_IT": "Sei un Sergente Krom'gar dell'armata del Supremo Krom'gar.",
    "ru_RU": "\u041a\u0440\u043e\u043c'\u0433\u0430\u0440\u0441\u043a\u0438\u0439 \u0441\u0435\u0440\u0436\u0430\u043d\u0442 \u0432 \u0430\u0440\u043c\u0438\u0438 \u0432\u043b\u0430\u0441\u0442\u0438\u0442\u0435\u043b\u044f \u041a\u0440\u043e\u043c\u0433\u0430\u0440\u0430.",
    "ko_KR": "\uad70\uc8fc \ud06c\ub86c\uac00\ub974\uc758 \ubd80\ub300\uc5d0 \uc788\ub294 \ud06c\ub86c\uac00\ub974 \ud558\uc0ac\uad00",
    "zh_TW": "\u9738\u4e3b\u514b\u7f85\u59c6\u52a0\u8ecd\u968a\u4e2d\u7684\u514b\u7f85\u59c6\u52a0\u58eb\u5b98\u3002",
    "zh_CN": "\u514b\u7f57\u59c6\u52a0\u5927\u738b\u519b\u961f\u4e2d\u7684\u514b\u7f57\u59c6\u52a0\u4e2d\u58eb\u3002"
  }
}